ezIncrementalBackup/__init__.py
ezIncrementalBackup/cli.py
ezIncrementalBackup/cli_wizard.py
ezIncrementalBackup/utils.py
ezIncrementalBackup/backup/__init__.py
ezIncrementalBackup/backup/compress.py
ezIncrementalBackup/backup/full.py
ezIncrementalBackup/backup/incremental.py
ezIncrementalBackup/backup/webdav.py
ezIncrementalBackup-1.2.0.dist-info/LICENSE
ezIncrementalBackup-1.2.0.dist-info/METADATA
ezIncrementalBackup-1.2.0.dist-info/WHEEL
ezIncrementalBackup-1.2.0.dist-info/entry_points.txt
ezIncrementalBackup-1.2.0.dist-info/top_level.txt
ezIncrementalBackup-1.2.0.dist-info/RECORD
