Metadata-Version: 2.1
Name: ezIncrementalBackup
Version: 1.2.0
Summary: 一个简单的增量备份工具
Author: DawnDream
Requires-Python: >=3.7
License-File: LICENSE
Requires-Dist: click
Requires-Dist: py7zr
Requires-Dist: webdavclient3
Requires-Dist: PyYAML
Requires-Dist: tqdm
Requires-Dist: questionary
